name_generator/__init__.py
name_generator/name_generator.py
src/__init__.py
src/name_generator.py
name_generator-0.1.1.dist-info/LICENSE
name_generator-0.1.1.dist-info/METADATA
name_generator-0.1.1.dist-info/WHEEL
name_generator-0.1.1.dist-info/top_level.txt
name_generator-0.1.1.dist-info/RECORD
